rtl/alu.v
module alu( input [3:0]a,[3:0]b,[2:0] opcode, output reg[3:0] result , reg carry, zero);
assign zero = (result == 4'b0000);
always @(*) begin
carry=0;
case(opcode) 
3'b000: {carry,result}=a+b;
3'b001: {carry,result}=a-b;
3'b010: result=a&b;
3'b011: result=a|b;
3'b100: result=a^b;
3'b101: result=~a;
default:result= 4'b0000;
endcase
end
endmodule

tb/alu_tb.v
`timescale 1ns/1ps

module alu_tb;

    reg  [3:0] a, b;
    reg  [2:0] opcode;
    wire [3:0] result;
    wire       carry, zero;

    integer pass_count, fail_count;

    alu uut (
        .a(a), .b(b),
        .opcode(opcode),
        .result(result),
        .carry(carry),
        .zero(zero)
    );

    initial begin
        $dumpfile("sim/waveform.vcd");
        $dumpvars(0, alu_tb);
    end

    initial begin
        pass_count = 0;
        fail_count = 0;

        $display("==============================");
        $display("   4-bit ALU Directed Tests   ");
        $display("==============================");

        // ── ADD ──────────────────────────────────
        $display("\n--- ADD ---");

        a=4;  b=4;  opcode=3'b000; #10;
        if(result==8 && carry==0) begin
            $display("PASS: ADD  4+4   = %0d", result);
            pass_count=pass_count+1;
        end else begin
            $display("FAIL: ADD  4+4   expected 8, got %0d", result);
            fail_count=fail_count+1;
        end

        a=0;  b=0;  opcode=3'b000; #10;
        if(result==0 && carry==0 && zero==1) begin
            $display("PASS: ADD  0+0   = %0d (zero=1)", result);
            pass_count=pass_count+1;
        end else begin
            $display("FAIL: ADD  0+0   expected 0, got %0d", result);
            fail_count=fail_count+1;
        end

        a=15; b=0;  opcode=3'b000; #10;
        if(result==15 && carry==0) begin
            $display("PASS: ADD  15+0  = %0d", result);
            pass_count=pass_count+1;
        end else begin
            $display("FAIL: ADD  15+0  expected 15, got %0d", result);
            fail_count=fail_count+1;
        end

        a=15; b=1;  opcode=3'b000; #10;
        if(result==0 && carry==1) begin
            $display("PASS: ADD  15+1  = %0d (carry=1 overflow)", result);
            pass_count=pass_count+1;
        end else begin
            $display("FAIL: ADD  15+1  expected 0 carry=1, got %0d carry=%b", result, carry);
            fail_count=fail_count+1;
        end

        a=15; b=15; opcode=3'b000; #10;
        if(result==14 && carry==1) begin
            $display("PASS: ADD  15+15 = %0d (carry=1)", result);
            pass_count=pass_count+1;
        end else begin
            $display("FAIL: ADD  15+15 expected 14 carry=1, got %0d carry=%b", result, carry);
            fail_count=fail_count+1;
        end

        // ── SUB ──────────────────────────────────
        $display("\n--- SUB ---");

        a=7;  b=3;  opcode=3'b001; #10;
        if(result==4) begin
            $display("PASS: SUB  7-3   = %0d", result);
            pass_count=pass_count+1;
        end else begin
            $display("FAIL: SUB  7-3   expected 4, got %0d", result);
            fail_count=fail_count+1;
        end

        a=5;  b=5;  opcode=3'b001; #10;
        if(result==0 && zero==1) begin
            $display("PASS: SUB  5-5   = %0d (zero=1)", result);
            pass_count=pass_count+1;
        end else begin
            $display("FAIL: SUB  5-5   expected 0, got %0d", result);
            fail_count=fail_count+1;
        end

        a=0;  b=0;  opcode=3'b001; #10;
        if(result==0 && zero==1) begin
            $display("PASS: SUB  0-0   = %0d (zero=1)", result);
            pass_count=pass_count+1;
        end else begin
            $display("FAIL: SUB  0-0   expected 0, got %0d", result);
            fail_count=fail_count+1;
        end

        a=3;  b=7;  opcode=3'b001; #10;
        if(result==4'b1100) begin
            $display("PASS: SUB  3-7   = %0d (underflow wraparound)", result);
            pass_count=pass_count+1;
        end else begin
            $display("FAIL: SUB  3-7   expected 12 underflow, got %0d", result);
            fail_count=fail_count+1;
        end

        // ── AND ──────────────────────────────────
        $display("\n--- AND ---");

        a=4'hA; b=4'h5; opcode=3'b010; #10;
        if(result==0 && zero==1) begin
            $display("PASS: AND  A&5   = %0d (zero=1)", result);
            pass_count=pass_count+1;
        end else begin
            $display("FAIL: AND  A&5   expected 0, got %0d", result);
            fail_count=fail_count+1;
        end

        a=4'hF; b=4'hF; opcode=3'b010; #10;
        if(result==4'hF) begin
            $display("PASS: AND  F&F   = %0d", result);
            pass_count=pass_count+1;
        end else begin
            $display("FAIL: AND  F&F   expected 15, got %0d", result);
            fail_count=fail_count+1;
        end

        a=4'hF; b=4'h0; opcode=3'b010; #10;
        if(result==0 && zero==1) begin
            $display("PASS: AND  F&0   = %0d (zero=1)", result);
            pass_count=pass_count+1;
        end else begin
            $display("FAIL: AND  F&0   expected 0, got %0d", result);
            fail_count=fail_count+1;
        end

        // ── OR ───────────────────────────────────
        $display("\n--- OR ---");

        a=4'hA; b=4'h5; opcode=3'b011; #10;
        if(result==4'hF) begin
            $display("PASS: OR   A|5   = %0d", result);
            pass_count=pass_count+1;
        end else begin
            $display("FAIL: OR   A|5   expected 15, got %0d", result);
            fail_count=fail_count+1;
        end

        a=0;    b=0;    opcode=3'b011; #10;
        if(result==0 && zero==1) begin
            $display("PASS: OR   0|0   = %0d (zero=1)", result);
            pass_count=pass_count+1;
        end else begin
            $display("FAIL: OR   0|0   expected 0, got %0d", result);
            fail_count=fail_count+1;
        end

        a=4'hF; b=4'h0; opcode=3'b011; #10;
        if(result==4'hF) begin
            $display("PASS: OR   F|0   = %0d", result);
            pass_count=pass_count+1;
        end else begin
            $display("FAIL: OR   F|0   expected 15, got %0d", result);
            fail_count=fail_count+1;
        end

        // ── NOT ──────────────────────────────────
        $display("\n--- NOT ---");

        a=4'b0100; b=0; opcode=3'b100; #10;
        if(result==4'b1011) begin
            $display("PASS: NOT  ~4    = %0d", result);
            pass_count=pass_count+1;
        end else begin
            $display("FAIL: NOT  ~4    expected 11, got %0d", result);
            fail_count=fail_count+1;
        end

        a=4'b0000; b=0; opcode=3'b100; #10;
        if(result==4'b1111) begin
            $display("PASS: NOT  ~0    = %0d", result);
            pass_count=pass_count+1;
        end else begin
            $display("FAIL: NOT  ~0    expected 15, got %0d", result);
            fail_count=fail_count+1;
        end

        a=4'b1111; b=0; opcode=3'b100; #10;
        if(result==4'b0000 && zero==1) begin
            $display("PASS: NOT  ~F    = %0d (zero=1)", result);
            pass_count=pass_count+1;
        end else begin
            $display("FAIL: NOT  ~F    expected 0, got %0d", result);
            fail_count=fail_count+1;
        end

        // ── XOR ──────────────────────────────────
        $display("\n--- XOR ---");

        a=4'hA; b=4'hA; opcode=3'b101; #10;
        if(result==0 && zero==1) begin
            $display("PASS: XOR  A^A   = %0d (zero=1)", result);
            pass_count=pass_count+1;
        end else begin
            $display("FAIL: XOR  A^A   expected 0, got %0d", result);
            fail_count=fail_count+1;
        end

        a=4'hA; b=4'h5; opcode=3'b101; #10;
        if(result==4'hF) begin
            $display("PASS: XOR  A^5   = %0d", result);
            pass_count=pass_count+1;
        end else begin
            $display("FAIL: XOR  A^5   expected 15, got %0d", result);
            fail_count=fail_count+1;
        end

        a=4'h0; b=4'hF; opcode=3'b101; #10;
        if(result==4'hF) begin
            $display("PASS: XOR  0^F   = %0d", result);
            pass_count=pass_count+1;
        end else begin
            $display("FAIL: XOR  0^F   expected 15, got %0d", result);
            fail_count=fail_count+1;
        end

        // ── Summary ──────────────────────────────
        $display("\n==============================");
        $display(" PASSED: %0d / %0d", pass_count, pass_count+fail_count);
        $display(" FAILED: %0d / %0d", fail_count, pass_count+fail_count);
        $display("==============================");

        $finish;
    end

endmodule

sim/waveform.vcd
$version Generated by VerilatedVcd $end
$timescale 1ps $end
 $scope module $rootio $end
 $upscope $end
 $scope module alu_tb $end
  $var wire 4 # a [3:0] $end
  $var wire 4 $ b [3:0] $end
  $var wire 3 % opcode [2:0] $end
  $var wire 4 ( result [3:0] $end
  $var wire 1 ) carry $end
  $var wire 1 * zero $end
  $var wire 32 & pass_count [31:0] $end
  $var wire 32 ' fail_count [31:0] $end
  $scope module uut $end
   $var wire 4 # a [3:0] $end
   $var wire 4 $ b [3:0] $end
   $var wire 3 % opcode [2:0] $end
   $var wire 4 ( result [3:0] $end
   $var wire 1 ) carry $end
   $var wire 1 * zero $end
  $upscope $end
 $upscope $end
$enddefinitions $end


#0
b0100 #
b0100 $
b000 %
b00000000000000000000000000000000 &
b00000000000000000000000000000000 '
b1000 (
0)
0*
#10000
b0000 #
b0000 $
b00000000000000000000000000000001 &
b0000 (
1*
#20000
b1111 #
b00000000000000000000000000000010 &
b1111 (
0*
#30000
b0001 $
b00000000000000000000000000000011 &
b0000 (
1)
1*
#40000
b1111 $
b00000000000000000000000000000100 &
b1110 (
0*
#50000
b0111 #
b0011 $
b001 %
b00000000000000000000000000000101 &
b0100 (
0)
#60000
b0101 #
b0101 $
b00000000000000000000000000000110 &
b0000 (
1*
#70000
b0000 #
b0000 $
b00000000000000000000000000000111 &
#80000
b0011 #
b0111 $
b00000000000000000000000000001000 &
b1100 (
1)
0*
#90000
b1010 #
b0101 $
b010 %
b00000000000000000000000000001001 &
b0000 (
0)
1*
#100000
b1111 #
b1111 $
b00000000000000000000000000001010 &
b1111 (
0*
#110000
b0000 $
b00000000000000000000000000001011 &
b0000 (
1*
#120000
b1010 #
b0101 $
b011 %
b00000000000000000000000000001100 &
b1111 (
0*
#130000
b0000 #
b0000 $
b00000000000000000000000000001101 &
b0000 (
1*
#140000
b1111 #
b00000000000000000000000000001110 &
b1111 (
0*
#150000
b0100 #
b100 %
b00000000000000000000000000001111 &
b1011 (
#160000
b0000 #
b00000000000000000000000000010000 &
b1111 (
#170000
b1111 #
b00000000000000000000000000010001 &
b0000 (
1*
#180000
b1010 #
b1010 $
b101 %
b00000000000000000000000000010010 &
#190000
b0101 $
b00000000000000000000000000010011 &
b1111 (
0*
#200000
b0000 #
b1111 $
b00000000000000000000000000010100 &
#210000
b00000000000000000000000000010101 &
