rtl/alu.v
module alu( input [3:0]a,[3:0]b,[2:0] opcode, output reg[3:0] result , reg carry, zero);
assign zero = (result == 4'b0000);
always @(*) begin
carry=0;
case(opcode) 
3'b000: {carry,result}=a+b;
3'b001: {carry,result}=a-b;
3'b010: result=a&b;
3'b011: result=a|b;
3'b100: result=a^b;
3'b101: result=~a;
default:result= 4'b0000;
endcase
end
endmodule

tb/alu_tb.v
`timescale 1ns/1ps

module alu_tb;

    reg  [3:0] a, b;
    reg  [2:0] opcode;
    wire [3:0] result;
    wire       carry, zero;
    reg  [3:0] expected;

    integer pass_count, fail_count;
    integer rand_pass,  rand_fail;

    alu uut (
        .a(a), .b(b),
        .opcode(opcode),
        .result(result),
        .carry(carry),
        .zero(zero)
    );

    initial begin
        $dumpfile("sim/waveform.vcd");
        $dumpvars(0, alu_tb);
    end

    // ── Directed Tests ────────────────────────────
    initial begin
        pass_count = 0;
        fail_count = 0;

        $display("==============================");
        $display("   4-bit ALU Directed Tests   ");
        $display("==============================");

        $display("\n--- ADD ---");
        a=4;  b=4;  opcode=3'b000; #10;
        if(result==8 && carry==0) begin
            $display("PASS: ADD  4+4   = %0d", result);
            pass_count=pass_count+1;
        end else begin
            $display("FAIL: ADD  4+4   expected 8, got %0d", result);
            fail_count=fail_count+1;
        end

        a=0;  b=0;  opcode=3'b000; #10;
        if(result==0 && carry==0 && zero==1) begin
            $display("PASS: ADD  0+0   = %0d (zero=1)", result);
            pass_count=pass_count+1;
        end else begin
            $display("FAIL: ADD  0+0   expected 0, got %0d", result);
            fail_count=fail_count+1;
        end

        a=15; b=0;  opcode=3'b000; #10;
        if(result==15 && carry==0) begin
            $display("PASS: ADD  15+0  = %0d", result);
            pass_count=pass_count+1;
        end else begin
            $display("FAIL: ADD  15+0  expected 15, got %0d", result);
            fail_count=fail_count+1;
        end

        a=15; b=1;  opcode=3'b000; #10;
        if(result==0 && carry==1) begin
            $display("PASS: ADD  15+1  = %0d (carry=1 overflow)", result);
            pass_count=pass_count+1;
        end else begin
            $display("FAIL: ADD  15+1  expected 0 carry=1, got %0d carry=%b", result, carry);
            fail_count=fail_count+1;
        end

        a=15; b=15; opcode=3'b000; #10;
        if(result==14 && carry==1) begin
            $display("PASS: ADD  15+15 = %0d (carry=1)", result);
            pass_count=pass_count+1;
        end else begin
            $display("FAIL: ADD  15+15 expected 14 carry=1, got %0d carry=%b", result, carry);
            fail_count=fail_count+1;
        end

        $display("\n--- SUB ---");
        a=7;  b=3;  opcode=3'b001; #10;
        if(result==4) begin
            $display("PASS: SUB  7-3   = %0d", result);
            pass_count=pass_count+1;
        end else begin
            $display("FAIL: SUB  7-3   expected 4, got %0d", result);
            fail_count=fail_count+1;
        end

        a=5;  b=5;  opcode=3'b001; #10;
        if(result==0 && zero==1) begin
            $display("PASS: SUB  5-5   = %0d (zero=1)", result);
            pass_count=pass_count+1;
        end else begin
            $display("FAIL: SUB  5-5   expected 0, got %0d", result);
            fail_count=fail_count+1;
        end

        a=0;  b=0;  opcode=3'b001; #10;
        if(result==0 && zero==1) begin
            $display("PASS: SUB  0-0   = %0d (zero=1)", result);
            pass_count=pass_count+1;
        end else begin
            $display("FAIL: SUB  0-0   expected 0, got %0d", result);
            fail_count=fail_count+1;
        end

        a=3;  b=7;  opcode=3'b001; #10;
        if(result==4'b1100) begin
            $display("PASS: SUB  3-7   = %0d (underflow wraparound)", result);
            pass_count=pass_count+1;
        end else begin
            $display("FAIL: SUB  3-7   expected 12 underflow, got %0d", result);
            fail_count=fail_count+1;
        end

        $display("\n--- AND ---");
        a=4'hA; b=4'h5; opcode=3'b010; #10;
        if(result==0 && zero==1) begin
            $display("PASS: AND  A&5   = %0d (zero=1)", result);
            pass_count=pass_count+1;
        end else begin
            $display("FAIL: AND  A&5   expected 0, got %0d", result);
            fail_count=fail_count+1;
        end

        a=4'hF; b=4'hF; opcode=3'b010; #10;
        if(result==4'hF) begin
            $display("PASS: AND  F&F   = %0d", result);
            pass_count=pass_count+1;
        end else begin
            $display("FAIL: AND  F&F   expected 15, got %0d", result);
            fail_count=fail_count+1;
        end

        a=4'hF; b=4'h0; opcode=3'b010; #10;
        if(result==0 && zero==1) begin
            $display("PASS: AND  F&0   = %0d (zero=1)", result);
            pass_count=pass_count+1;
        end else begin
            $display("FAIL: AND  F&0   expected 0, got %0d", result);
            fail_count=fail_count+1;
        end

        $display("\n--- OR ---");
        a=4'hA; b=4'h5; opcode=3'b011; #10;
        if(result==4'hF) begin
            $display("PASS: OR   A|5   = %0d", result);
            pass_count=pass_count+1;
        end else begin
            $display("FAIL: OR   A|5   expected 15, got %0d", result);
            fail_count=fail_count+1;
        end

        a=0;    b=0;    opcode=3'b011; #10;
        if(result==0 && zero==1) begin
            $display("PASS: OR   0|0   = %0d (zero=1)", result);
            pass_count=pass_count+1;
        end else begin
            $display("FAIL: OR   0|0   expected 0, got %0d", result);
            fail_count=fail_count+1;
        end

        a=4'hF; b=4'h0; opcode=3'b011; #10;
        if(result==4'hF) begin
            $display("PASS: OR   F|0   = %0d", result);
            pass_count=pass_count+1;
        end else begin
            $display("FAIL: OR   F|0   expected 15, got %0d", result);
            fail_count=fail_count+1;
        end

        $display("\n--- NOT ---");
        a=4'b0100; b=0; opcode=3'b100; #10;
        if(result==4'b1011) begin
            $display("PASS: NOT  ~4    = %0d", result);
            pass_count=pass_count+1;
        end else begin
            $display("FAIL: NOT  ~4    expected 11, got %0d", result);
            fail_count=fail_count+1;
        end

        a=4'b0000; b=0; opcode=3'b100; #10;
        if(result==4'b1111) begin
            $display("PASS: NOT  ~0    = %0d", result);
            pass_count=pass_count+1;
        end else begin
            $display("FAIL: NOT  ~0    expected 15, got %0d", result);
            fail_count=fail_count+1;
        end

        a=4'b1111; b=0; opcode=3'b100; #10;
        if(result==4'b0000 && zero==1) begin
            $display("PASS: NOT  ~F    = %0d (zero=1)", result);
            pass_count=pass_count+1;
        end else begin
            $display("FAIL: NOT  ~F    expected 0, got %0d", result);
            fail_count=fail_count+1;
        end

        $display("\n--- XOR ---");
        a=4'hA; b=4'hA; opcode=3'b101; #10;
        if(result==0 && zero==1) begin
            $display("PASS: XOR  A^A   = %0d (zero=1)", result);
            pass_count=pass_count+1;
        end else begin
            $display("FAIL: XOR  A^A   expected 0, got %0d", result);
            fail_count=fail_count+1;
        end

        a=4'hA; b=4'h5; opcode=3'b101; #10;
        if(result==4'hF) begin
            $display("PASS: XOR  A^5   = %0d", result);
            pass_count=pass_count+1;
        end else begin
            $display("FAIL: XOR  A^5   expected 15, got %0d", result);
            fail_count=fail_count+1;
        end

        a=4'h0; b=4'hF; opcode=3'b101; #10;
        if(result==4'hF) begin
            $display("PASS: XOR  0^F   = %0d", result);
            pass_count=pass_count+1;
        end else begin
            $display("FAIL: XOR  0^F   expected 15, got %0d", result);
            fail_count=fail_count+1;
        end

        $display("\n==============================");
        $display(" DIRECTED TESTS");
        $display(" PASSED: %0d / %0d", pass_count, pass_count+fail_count);
        $display(" FAILED: %0d / %0d", fail_count, pass_count+fail_count);
        $display("==============================");
    end

    // ── Random Verification ───────────────────────
    initial begin
        rand_pass = 0;
        rand_fail = 0;

        #5000; // wait for directed tests to finish

        $display("\n==============================");
        $display("   4-bit ALU Random Tests     ");
        $display("==============================");

        /* verilator lint_off WIDTHTRUNC */
        repeat(500) begin
            a      = $random;
            b      = $random;
            opcode = $random % 6;
            #10;

            case(opcode)
                3'b000: expected = a + b;
                3'b001: expected = a - b;
                3'b010: expected = a & b;
                3'b011: expected = a | b;
                3'b100: expected = ~a;
                3'b101: expected = a ^ b;
                default: expected = 4'b0000;
            endcase

            if(result == expected) begin
                rand_pass = rand_pass + 1;
            end else begin
                rand_fail = rand_fail + 1;
                $display("FAIL: op=%0d a=%0d b=%0d expected=%0d got=%0d",
                          opcode, a, b, expected, result);
            end
        end
        /* verilator lint_on WIDTHTRUNC */

        $display("\n==============================");
        $display(" RANDOM TESTS (500 vectors)");
        $display(" PASSED: %0d / 500", rand_pass);
        $display(" FAILED: %0d / 500", rand_fail);
        $display("==============================");
        $finish;
    end

endmodule

sim/waveform.vcd
$version Generated by VerilatedVcd $end
$timescale 1ps $end
 $scope module $rootio $end
 $upscope $end
 $scope module alu_tb $end
  $var wire 4 # a [3:0] $end
  $var wire 4 $ b [3:0] $end
  $var wire 3 % opcode [2:0] $end
  $var wire 4 & result [3:0] $end
  $var wire 1 ' carry $end
  $var wire 1 ( zero $end
  $var wire 4 ) expected [3:0] $end
  $var wire 32 * pass_count [31:0] $end
  $var wire 32 + fail_count [31:0] $end
  $var wire 32 , rand_pass [31:0] $end
  $var wire 32 - rand_fail [31:0] $end
  $scope module uut $end
   $var wire 4 # a [3:0] $end
   $var wire 4 $ b [3:0] $end
   $var wire 3 % opcode [2:0] $end
   $var wire 4 & result [3:0] $end
   $var wire 1 ' carry $end
   $var wire 1 ( zero $end
  $upscope $end
 $upscope $end
$enddefinitions $end


#0
b0100 #
b0100 $
b000 %
b1000 &
0'
0(
b0000 )
b00000000000000000000000000000000 *
b00000000000000000000000000000000 +
b00000000000000000000000000000000 ,
b00000000000000000000000000000000 -
#10000
b0000 #
b0000 $
b0000 &
1(
b00000000000000000000000000000001 *
#20000
b1111 #
b1111 &
0(
b00000000000000000000000000000010 *
#30000
b0001 $
b0000 &
1'
1(
b00000000000000000000000000000011 *
#40000
b1111 $
b1110 &
0(
b00000000000000000000000000000100 *
#50000
b0111 #
b0011 $
b001 %
b0100 &
0'
b00000000000000000000000000000101 *
#60000
b0101 #
b0101 $
b0000 &
1(
b00000000000000000000000000000110 *
#70000
b0000 #
b0000 $
b00000000000000000000000000000111 *
#80000
b0011 #
b0111 $
b1100 &
1'
0(
b00000000000000000000000000001000 *
#90000
b1010 #
b0101 $
b010 %
b0000 &
0'
1(
b00000000000000000000000000001001 *
#100000
b1111 #
b1111 $
b1111 &
0(
b00000000000000000000000000001010 *
#110000
b0000 $
b0000 &
1(
b00000000000000000000000000001011 *
#120000
b1010 #
b0101 $
b011 %
b1111 &
0(
b00000000000000000000000000001100 *
#130000
b0000 #
b0000 $
b0000 &
1(
b00000000000000000000000000001101 *
#140000
b1111 #
b1111 &
0(
b00000000000000000000000000001110 *
#150000
b0100 #
b100 %
b1011 &
b00000000000000000000000000001111 *
#160000
b0000 #
b1111 &
b00000000000000000000000000010000 *
#170000
b1111 #
b0000 &
1(
b00000000000000000000000000010001 *
#180000
b1010 #
b1010 $
b101 %
b00000000000000000000000000010010 *
#190000
b0101 $
b1111 &
0(
b00000000000000000000000000010011 *
#200000
b0000 #
b1111 $
b00000000000000000000000000010100 *
#210000
b00000000000000000000000000010101 *
#5000000
b0100 #
b1100 $
b110 %
b0000 &
1(
#5010000
b1000 $
b000 %
b1100 &
0(
b00000000000000000000000000000001 ,
#5020000
b0110 #
b0100 $
b101 %
b0010 &
b1100 )
b00000000000000000000000000000010 ,
#5030000
b0011 #
b0001 $
b111 %
b0000 &
1(
b0010 )
b00000000000000000000000000000011 ,
#5040000
b0101 #
b0010 $
b000 %
b0111 &
0(
b0000 )
b00000000000000000000000000000100 ,
#5050000
b100 %
b1010 &
b0111 )
b00000000000000000000000000000101 ,
#5060000
b1101 #
b0100 $
b011 %
b1101 &
b1010 )
b00000000000000000000000000000110 ,
#5070000
b1000 #
b0010 $
b010 %
b0000 &
1(
b1101 )
b00000000000000000000000000000111 ,
#5080000
b1110 #
b1110 $
b1110 &
0(
b0000 )
b00000000000000000000000000001000 ,
#5090000
b0000 $
b0000 &
1(
b1110 )
b00000000000000000000000000001001 ,
#5100000
b0011 #
b011 %
b0011 &
0(
b0000 )
b00000000000000000000000000001010 ,
#5110000
b0010 #
b0110 $
b111 %
b0000 &
1(
b0011 )
b00000000000000000000000000001011 ,
#5120000
b0011 #
b1000 $
b011 %
b1011 &
0(
b0000 )
b00000000000000000000000000001100 ,
#5130000
b1110 #
b0111 $
b1111 &
b1011 )
b00000000000000000000000000001101 ,
#5140000
b100 %
b0001 &
b1111 )
b00000000000000000000000000001110 ,
#5150000
b1000 #
b1111 $
b101 %
b0111 &
b0001 )
b00000000000000000000000000001111 ,
#5160000
b0100 #
b0010 $
b100 %
b1011 &
b0111 )
b00000000000000000000000000010000 ,
#5170000
b1111 #
b1001 $
b101 %
b0110 &
b1011 )
b00000000000000000000000000010001 ,
#5180000
b0100 $
b1011 &
b0110 )
b00000000000000000000000000010010 ,
#5190000
b0011 #
b1011 $
b000 %
b1110 &
b1011 )
b00000000000000000000000000010011 ,
#5200000
b1001 $
b011 %
b1011 &
b1110 )
b00000000000000000000000000010100 ,
#5210000
b1010 #
b1101 $
b101 %
b0111 &
b1011 )
b00000000000000000000000000010101 ,
#5220000
b0100 #
b1111 $
b001 %
b0101 &
1'
b0111 )
b00000000000000000000000000010110 ,
#5230000
b1101 #
b1001 $
b000 %
b0110 &
b0101 )
b00000000000000000000000000010111 ,
#5240000
b1010 #
b0010 $
b110 %
b0000 &
0'
1(
b0110 )
b00000000000000000000000000011000 ,
#5250000
b0100 #
b0011 $
b101 %
b0111 &
0(
b0000 )
b00000000000000000000000000011001 ,
#5260000
b0011 #
b1101 $
b1110 &
b0111 )
b00000000000000000000000000011010 ,
#5270000
b1110 #
b1111 $
b0001 &
b1110 )
b00000000000000000000000000011011 ,
#5280000
b0111 #
b1001 $
b000 %
b0000 &
1'
1(
b0001 )
b00000000000000000000000000011100 ,
#5290000
b1111 #
b1111 $
b001 %
0'
b0000 )
b00000000000000000000000000011101 ,
#5300000
b010 %
b1111 &
0(
b00000000000000000000000000011110 ,
#5310000
b0111 #
b1010 $
b001 %
b1101 &
1'
b1111 )
b00000000000000000000000000011111 ,
#5320000
b0011 #
b1111 $
b110 %
b0000 &
0'
1(
b1101 )
b00000000000000000000000000100000 ,
#5330000
b0010 #
b1011 $
b100 %
b1101 &
0(
b0000 )
b00000000000000000000000000100001 ,
#5340000
b1101 $
b1101 )
b00000000000000000000000000100010 ,
#5350000
b0100 #
b0001 $
b011 %
b0101 &
b00000000000000000000000000100011 ,
#5360000
b0001 #
b0011 $
b0011 &
b0101 )
b00000000000000000000000000100100 ,
#5370000
b0101 #
b1101 $
b100 %
b1010 &
b0011 )
b00000000000000000000000000100101 ,
#5380000
b0010 #
b1010 $
b1101 &
b1010 )
b00000000000000000000000000100110 ,
#5390000
b0101 #
b1000 $
b000 %
b1101 )
b00000000000000000000000000100111 ,
#5400000
b0000 #
b0011 $
b110 %
b0000 &
1(
b00000000000000000000000000101000 ,
#5410000
b1101 #
b1100 $
b000 %
b1001 &
1'
0(
b0000 )
b00000000000000000000000000101001 ,
#5420000
b0111 #
b0111 $
b101 %
b0000 &
0'
1(
b1001 )
b00000000000000000000000000101010 ,
#5430000
b0000 #
b0011 $
b110 %
b0000 )
b00000000000000000000000000101011 ,
#5440000
b0110 #
b0111 $
b000 %
b1101 &
0(
b00000000000000000000000000101100 ,
#5450000
b0111 #
b0011 $
b110 %
b0000 &
1(
b1101 )
b00000000000000000000000000101101 ,
#5460000
b0100 #
b0100 $
b0000 )
b00000000000000000000000000101110 ,
#5470000
b0111 #
b0101 $
b000 %
b1100 &
0(
b00000000000000000000000000101111 ,
#5480000
b0100 #
b010 %
b0100 &
b1100 )
b00000000000000000000000000110000 ,
#5490000
b1101 #
b1111 $
b011 %
b1111 &
b0100 )
b00000000000000000000000000110001 ,
#5500000
b1100 #
b1100 $
b110 %
b0000 &
1(
b1111 )
b00000000000000000000000000110010 ,
#5510000
b0110 #
b1001 $
b100 %
b1001 &
0(
b0000 )
b00000000000000000000000000110011 ,
#5520000
b0100 #
b0100 $
b001 %
b0000 &
1(
b1001 )
b00000000000000000000000000110100 ,
#5530000
b1011 #
b0010 $
b011 %
b1011 &
0(
b0000 )
b00000000000000000000000000110101 ,
#5540000
b0011 #
b0011 $
b100 %
b1100 &
b1011 )
b00000000000000000000000000110110 ,
#5550000
b0000 #
b0100 $
b001 %
1'
b1100 )
b00000000000000000000000000110111 ,
#5560000
b1000 #
b0011 $
b100 %
b0111 &
0'
b00000000000000000000000000111000 ,
#5570000
b0001 #
b0001 $
b111 %
b0000 &
1(
b0111 )
b00000000000000000000000000111001 ,
#5580000
b0010 #
b1100 $
b000 %
b1110 &
0(
b0000 )
b00000000000000000000000000111010 ,
#5590000
b1011 #
b0001 $
b1100 &
b1110 )
b00000000000000000000000000111011 ,
#5600000
b1101 #
b0100 $
b0001 &
1'
b1100 )
b00000000000000000000000000111100 ,
#5610000
b101 %
b1001 &
0'
b0001 )
b00000000000000000000000000111101 ,
#5620000
b1011 #
b1011 $
b011 %
b1011 &
b1001 )
b00000000000000000000000000111110 ,
#5630000
b1110 #
b0100 $
b110 %
b0000 &
1(
b1011 )
b00000000000000000000000000111111 ,
#5640000
b0111 #
b0000 $
b100 %
b1000 &
0(
b0000 )
b00000000000000000000000001000000 ,
#5650000
b1111 #
b1001 $
b011 %
b1111 &
b1000 )
b00000000000000000000000001000001 ,
#5660000
b0111 #
b1010 $
b110 %
b0000 &
1(
b1111 )
b00000000000000000000000001000010 ,
#5670000
b1100 #
b0010 $
b100 %
b0011 &
0(
b0000 )
b00000000000000000000000001000011 ,
#5680000
b0110 #
b1011 $
b101 %
b1101 &
b0011 )
b00000000000000000000000001000100 ,
#5690000
b0010 #
b0010 $
b110 %
b0000 &
1(
b1101 )
b00000000000000000000000001000101 ,
#5700000
b1001 #
b1111 $
b000 %
b1000 &
1'
0(
b0000 )
b00000000000000000000000001000110 ,
#5710000
b0100 #
b1001 $
b101 %
b1101 &
0'
b1000 )
b00000000000000000000000001000111 ,
#5720000
b1100 #
b0000 $
b1100 &
b1101 )
b00000000000000000000000001001000 ,
#5730000
b1010 #
b1101 $
b011 %
b1111 &
b1100 )
b00000000000000000000000001001001 ,
#5740000
b1001 #
b0000 $
b100 %
b0110 &
b1111 )
b00000000000000000000000001001010 ,
#5750000
b0110 #
b1011 $
b110 %
b0000 &
1(
b0110 )
b00000000000000000000000001001011 ,
#5760000
b1100 #
b0111 $
b010 %
b0100 &
0(
b0000 )
b00000000000000000000000001001100 ,
#5770000
b0100 #
b0001 $
b011 %
b0101 &
b0100 )
b00000000000000000000000001001101 ,
#5780000
b1001 #
b0000 $
b010 %
b0000 &
1(
b0101 )
b00000000000000000000000001001110 ,
#5790000
b0001 #
b1010 $
b011 %
b1011 &
0(
b0000 )
b00000000000000000000000001001111 ,
#5800000
b1100 #
b0110 $
b100 %
b0011 &
b1011 )
b00000000000000000000000001010000 ,
#5810000
b0110 #
b1110 $
b001 %
b1000 &
1'
b0011 )
b00000000000000000000000001010001 ,
#5820000
b1110 #
b1101 $
b000 %
b1011 &
b1000 )
b00000000000000000000000001010010 ,
#5830000
b0100 #
b011 %
b1101 &
0'
b1011 )
b00000000000000000000000001010011 ,
#5840000
b0110 #
b1110 $
b001 %
b1000 &
1'
b1101 )
b00000000000000000000000001010100 ,
#5850000
b0010 #
b0111 $
b110 %
b0000 &
0'
1(
b1000 )
b00000000000000000000000001010101 ,
#5860000
b0100 #
b1001 $
b001 %
b1011 &
1'
0(
b0000 )
b00000000000000000000000001010110 ,
#5870000
b0000 #
b0011 $
b100 %
b1111 &
0'
b1011 )
b00000000000000000000000001010111 ,
#5880000
b0110 #
b0111 $
b111 %
b0000 &
1(
b1111 )
b00000000000000000000000001011000 ,
#5890000
b0010 #
b0011 $
b100 %
b1101 &
0(
b0000 )
b00000000000000000000000001011001 ,
#5900000
b1110 #
b0100 $
b011 %
b1110 &
b1101 )
b00000000000000000000000001011010 ,
#5910000
b0000 #
b1001 $
b101 %
b1001 &
b1110 )
b00000000000000000000000001011011 ,
#5920000
b1001 #
b1000 $
b011 %
b1001 )
b00000000000000000000000001011100 ,
#5930000
b0110 #
b0000 $
b100 %
b00000000000000000000000001011101 ,
#5940000
b1101 #
b1110 $
b101 %
b0011 &
b00000000000000000000000001011110 ,
#5950000
b0000 #
b1101 $
b001 %
1'
b0011 )
b00000000000000000000000001011111 ,
#5960000
b1010 #
b1111 $
b100 %
b0101 &
0'
b00000000000000000000000001100000 ,
#5970000
b1000 #
b1100 $
b011 %
b1100 &
b0101 )
b00000000000000000000000001100001 ,
#5980000
b0100 #
b1001 $
b111 %
b0000 &
1(
b1100 )
b00000000000000000000000001100010 ,
#5990000
b1100 #
b110 %
b0000 )
b00000000000000000000000001100011 ,
#6000000
b1111 #
b1111 $
b001 %
b00000000000000000000000001100100 ,
#6010000
b1100 #
b1000 $
b011 %
b1100 &
0(
b00000000000000000000000001100101 ,
#6020000
b1000 #
b1001 $
b110 %
b0000 &
1(
b1100 )
b00000000000000000000000001100110 ,
#6030000
b0101 #
b0111 $
b101 %
b0010 &
0(
b0000 )
b00000000000000000000000001100111 ,
#6040000
b1111 #
b0001 $
b100 %
b0000 &
1(
b0010 )
b00000000000000000000000001101000 ,
#6050000
b0011 #
b0011 $
b001 %
b0000 )
b00000000000000000000000001101001 ,
#6060000
b1011 #
b0111 $
b010 %
b0011 &
0(
b00000000000000000000000001101010 ,
#6070000
b1001 #
b1010 $
b001 %
b1111 &
1'
b0011 )
b00000000000000000000000001101011 ,
#6080000
b1010 #
b1110 $
b1100 &
b1111 )
b00000000000000000000000001101100 ,
#6090000
b1111 #
b1001 $
b0110 &
0'
b1100 )
b00000000000000000000000001101101 ,
#6100000
b0000 #
b0110 $
b101 %
b0110 )
b00000000000000000000000001101110 ,
#6110000
b0001 #
b0001 $
b0000 &
1(
b00000000000000000000000001101111 ,
#6120000
b0010 #
b0100 $
b110 %
b0000 )
b00000000000000000000000001110000 ,
#6130000
b1110 #
b0111 $
b101 %
b1001 &
0(
b00000000000000000000000001110001 ,
#6140000
b1011 #
b1100 $
b000 %
b0111 &
1'
b1001 )
b00000000000000000000000001110010 ,
#6150000
b1000 #
b1101 $
b001 %
b1011 &
b0111 )
b00000000000000000000000001110011 ,
#6160000
b0100 #
b0000 $
b101 %
b0100 &
0'
b1011 )
b00000000000000000000000001110100 ,
#6170000
b0001 #
b1011 $
b1010 &
b0100 )
b00000000000000000000000001110101 ,
#6180000
b0111 #
b1100 $
b110 %
b0000 &
1(
b1010 )
b00000000000000000000000001110110 ,
#6190000
b1101 #
b1000 $
b0000 )
b00000000000000000000000001110111 ,
#6200000
b1100 #
b1011 $
b000 %
b0111 &
1'
0(
b00000000000000000000000001111000 ,
#6210000
b0100 #
b0110 $
b101 %
b0010 &
0'
b0111 )
b00000000000000000000000001111001 ,
#6220000
b1110 $
b100 %
b1011 &
b0010 )
b00000000000000000000000001111010 ,
#6230000
b1011 #
b1001 $
b000 %
b0100 &
1'
b1011 )
b00000000000000000000000001111011 ,
#6240000
b1100 #
b0001 $
b001 %
b1011 &
0'
b0100 )
b00000000000000000000000001111100 ,
#6250000
b0111 #
b1000 $
b000 %
b1111 &
b1011 )
b00000000000000000000000001111101 ,
#6260000
b0110 #
b0100 $
b100 %
b1001 &
b1111 )
b00000000000000000000000001111110 ,
#6270000
b1100 #
b1100 $
b101 %
b0000 &
1(
b1001 )
b00000000000000000000000001111111 ,
#6280000
b0010 #
b0000 $
b000 %
b0010 &
0(
b0000 )
b00000000000000000000000010000000 ,
#6290000
b1100 #
b0101 $
b111 %
b0000 &
1(
b0010 )
b00000000000000000000000010000001 ,
#6300000
b1101 #
b0011 $
b100 %
b0010 &
0(
b0000 )
b00000000000000000000000010000010 ,
#6310000
b0100 #
b0101 $
b110 %
b0000 &
1(
b0010 )
b00000000000000000000000010000011 ,
#6320000
b1011 #
b0001 $
b000 %
b1100 &
0(
b0000 )
b00000000000000000000000010000100 ,
#6330000
b0100 #
b1011 $
b101 %
b1111 &
b1100 )
b00000000000000000000000010000101 ,
#6340000
b0101 #
b0001 $
b000 %
b0110 &
b1111 )
b00000000000000000000000010000110 ,
#6350000
b1010 #
b0100 $
b101 %
b1110 &
b0110 )
b00000000000000000000000010000111 ,
#6360000
b0001 #
b0000 $
b111 %
b0000 &
1(
b1110 )
b00000000000000000000000010001000 ,
#6370000
b1010 #
b1100 $
b101 %
b0110 &
0(
b0000 )
b00000000000000000000000010001001 ,
#6380000
b1111 #
b0010 $
b100 %
b0000 &
1(
b0110 )
b00000000000000000000000010001010 ,
#6390000
b0100 #
b1000 $
b000 %
b1100 &
0(
b0000 )
b00000000000000000000000010001011 ,
#6400000
b1101 #
b0100 $
b011 %
b1101 &
b1100 )
b00000000000000000000000010001100 ,
#6410000
b1100 #
b1011 $
b001 %
b0001 &
b1101 )
b00000000000000000000000010001101 ,
#6420000
b0100 #
b0110 $
b101 %
b0010 &
b0001 )
b00000000000000000000000010001110 ,
#6430000
b1001 #
b1001 $
b100 %
b0110 &
b0010 )
b00000000000000000000000010001111 ,
#6440000
b0111 #
b0110 $
b101 %
b0001 &
b0110 )
b00000000000000000000000010010000 ,
#6450000
b0100 #
b1100 $
b1000 &
b0001 )
b00000000000000000000000010010001 ,
#6460000
b1100 #
b0000 $
b111 %
b0000 &
1(
b1000 )
b00000000000000000000000010010010 ,
#6470000
b1110 #
b1011 $
b000 %
b1001 &
1'
0(
b0000 )
b00000000000000000000000010010011 ,
#6480000
b1100 #
b1110 $
b011 %
b1110 &
0'
b1001 )
b00000000000000000000000010010100 ,
#6490000
b0001 #
b0101 $
b110 %
b0000 &
1(
b1110 )
b00000000000000000000000010010101 ,
#6500000
b0100 #
b0010 $
b011 %
b0110 &
0(
b0000 )
b00000000000000000000000010010110 ,
#6510000
b1001 #
b0011 $
b001 %
b0110 )
b00000000000000000000000010010111 ,
#6520000
b0010 #
b0000 $
b010 %
b0000 &
1(
b00000000000000000000000010011000 ,
#6530000
b1010 $
b000 %
b1100 &
0(
b0000 )
b00000000000000000000000010011001 ,
#6540000
b0111 #
b1110 $
b0101 &
1'
b1100 )
b00000000000000000000000010011010 ,
#6550000
b0101 #
b0011 $
b001 %
b0010 &
0'
b0101 )
b00000000000000000000000010011011 ,
#6560000
b1011 #
b1001 $
b100 %
b0100 &
b0010 )
b00000000000000000000000010011100 ,
#6570000
b0001 #
b1000 $
b000 %
b1001 &
b0100 )
b00000000000000000000000010011101 ,
#6580000
b1001 #
b0101 $
b001 %
b0100 &
b1001 )
b00000000000000000000000010011110 ,
#6590000
b0101 #
b1010 $
b000 %
b1111 &
b0100 )
b00000000000000000000000010011111 ,
#6600000
b0111 #
b1000 $
b101 %
b1111 )
b00000000000000000000000010100000 ,
#6610000
b0000 #
b1011 $
b010 %
b0000 &
1(
b00000000000000000000000010100001 ,
#6620000
b1100 #
b1111 $
b111 %
b0000 )
b00000000000000000000000010100010 ,
#6630000
b0010 $
b000 %
b1110 &
0(
b00000000000000000000000010100011 ,
#6640000
b1001 #
b1110 $
b001 %
b1011 &
1'
b1110 )
b00000000000000000000000010100100 ,
#6650000
b1011 #
b1010 $
b100 %
b0100 &
0'
b1011 )
b00000000000000000000000010100101 ,
#6660000
b0101 #
b1100 $
b1010 &
b0100 )
b00000000000000000000000010100110 ,
#6670000
b1001 #
b1010 $
b011 %
b1011 &
b1010 )
b00000000000000000000000010100111 ,
#6680000
b0011 #
b1110 $
b111 %
b0000 &
1(
b1011 )
b00000000000000000000000010101000 ,
#6690000
b1100 #
b1010 $
b110 %
b0000 )
b00000000000000000000000010101001 ,
#6700000
b1111 #
b0000 $
b011 %
b1111 &
0(
b00000000000000000000000010101010 ,
#6710000
b0010 #
b0100 $
b100 %
b1101 &
b1111 )
b00000000000000000000000010101011 ,
#6720000
b0101 #
b0011 $
b110 %
b0000 &
1(
b1101 )
b00000000000000000000000010101100 ,
#6730000
b1000 #
b1101 $
b011 %
b1101 &
0(
b0000 )
b00000000000000000000000010101101 ,
#6740000
b1001 #
b101 %
b0100 &
b1101 )
b00000000000000000000000010101110 ,
#6750000
b1100 #
b1000 $
b000 %
1'
b0100 )
b00000000000000000000000010101111 ,
#6760000
b1110 #
b1010 $
b010 %
b1010 &
0'
b00000000000000000000000010110000 ,
#6770000
b0100 #
b0111 $
b011 %
b0111 &
b1010 )
b00000000000000000000000010110001 ,
#6780000
b0101 #
b1000 $
b100 %
b1010 &
b0111 )
b00000000000000000000000010110010 ,
#6790000
b1000 #
b1110 $
b111 %
b0000 &
1(
b1010 )
b00000000000000000000000010110011 ,
#6800000
b1101 #
b0000 $
b110 %
b0000 )
b00000000000000000000000010110100 ,
#6810000
b0000 #
b1010 $
b011 %
b1010 &
0(
b00000000000000000000000010110101 ,
#6820000
b1010 #
b0010 $
b001 %
b1000 &
b1010 )
b00000000000000000000000010110110 ,
#6830000
b1111 #
b1110 $
b000 %
b1101 &
1'
b1000 )
b00000000000000000000000010110111 ,
#6840000
b1001 #
b1000 $
b011 %
b1001 &
0'
b1101 )
b00000000000000000000000010111000 ,
#6850000
b1111 #
b1010 $
b000 %
1'
b1001 )
b00000000000000000000000010111001 ,
#6860000
b1100 #
b0111 $
b100 %
b0011 &
0'
b00000000000000000000000010111010 ,
#6870000
b1010 #
b1111 $
b000 %
b1001 &
1'
b0011 )
b00000000000000000000000010111011 ,
#6880000
b1000 #
b1010 $
b0010 &
b1001 )
b00000000000000000000000010111100 ,
#6890000
b1110 #
b1100 $
b101 %
0'
b0010 )
b00000000000000000000000010111101 ,
#6900000
b0011 #
b1010 $
b000 %
b1101 &
b00000000000000000000000010111110 ,
#6910000
b1001 #
b0101 $
b101 %
b1100 &
b1101 )
b00000000000000000000000010111111 ,
#6920000
b1100 #
b1000 $
b000 %
b0100 &
1'
b1100 )
b00000000000000000000000011000000 ,
#6930000
b1000 #
b1101 $
b001 %
b1011 &
b0100 )
b00000000000000000000000011000001 ,
#6940000
b0001 $
b000 %
b1001 &
0'
b1011 )
b00000000000000000000000011000010 ,
#6950000
b0000 #
b0111 $
b011 %
b0111 &
b1001 )
b00000000000000000000000011000011 ,
